msb_client/ComplexDataFormat.py
msb_client/DataFormat.py
msb_client/DataType.py
msb_client/Event.py
msb_client/Function.py
msb_client/MsbClient.py
msb_client/__init__.py
msb_client/event_schema.json
msb_client/function_schema.json
msb_client-0.7.5.dist-info/METADATA
msb_client-0.7.5.dist-info/RECORD
msb_client-0.7.5.dist-info/WHEEL
msb_client-0.7.5.dist-info/top_level.txt
